ccluster/__init__.py
ccluster/size/__init__.py
ccluster/size/cbase.py
ccluster/size/ckmeans.py
ccluster/size/cspectral.py
ccluster-0.1.3.dist-info/LICENCE.txt
ccluster-0.1.3.dist-info/METADATA
ccluster-0.1.3.dist-info/WHEEL
ccluster-0.1.3.dist-info/top_level.txt
ccluster-0.1.3.dist-info/RECORD
