Metadata-Version: 2.1
Name: ccluster
Version: 0.1.3
Summary: A package for clustering with cluster size constraints.
Author: Chakib Fettal
Project-URL: Homepage, https://github.com/chakib401/ccluster
Requires-Python: >=3.10
License-File: LICENCE.txt
